README.rst
setup.py
django_admin_log.egg-info/PKG-INFO
django_admin_log.egg-info/SOURCES.txt
django_admin_log.egg-info/dependency_links.txt
django_admin_log.egg-info/pbr.json
django_admin_log.egg-info/top_level.txt
log/__init__.py
log/admin.py
log/models.py
log/tests.py
log/utils.py