Metadata-Version: 1.1
Name: django-admin-log
Version: 0.2
Summary: Application that logs errors generated in a web system into a model. The model is displayed in the administrator.
Home-page: https://github.com/mapeveri/django-admin-log
Author: Peveri Martin
Author-email: martinpeveri@gmail.com
License: BSD License
Platform: UNKNOWN
Classifier: Environment :: Web Environment
Classifier: Framework :: Django
Classifier: Intended Audience :: Developers
Classifier: License :: OSI Approved :: BSD License
Classifier: Operating System :: OS Independent
Classifier: Programming Language :: Python
Classifier: Programming Language :: Python :: 2.7
Classifier: Topic :: Internet :: WWW/HTTP
Classifier: Topic :: Internet :: WWW/HTTP :: Dynamic Content
